netsci/__init__.py
netsci/system_info.py
netsci/datasets/__init__.py
netsci/datasets/datasets.py
netsci/metrics/__init__.py
netsci/metrics/motifs.py
netsci/metrics/motifs_matmul.py
netsci/metrics/tensorians.py
netsci/models/__init__.py
netsci/models/random.py
netsci/resources/datasets/connectome.L5_TTPC.neurons.csv.gz
netsci/resources/datasets/connectome.L5_TTPC.synapses.csv.gz
netsci/resources/datasets/connectome.L6_LBC.neurons.csv.gz
netsci/resources/datasets/connectome.L6_LBC.synapses.csv.gz
netsci/tests/__init__.py
netsci/tests/profiler.py
netsci/tests/datasets/__init__.py
netsci/tests/datasets/test_connectomics.py
netsci/tests/metrics/__init__.py
netsci/tests/metrics/explore_motifs_tree.py
netsci/tests/metrics/profile_motifs.py
netsci/tests/metrics/profile_motifs_gpu.py
netsci/tests/metrics/test_motifs.py
netsci/tests/metrics/test_motifs_gpu.py
netsci/tests/metrics/test_motifs_identify_triad_node_roles.py
netsci/tests/metrics/test_motifs_with_participation.py
netsci/visualization/__init__.py
netsci/visualization/motifs.py
netsci/visualization/networks.py
netsci/visualization/node.py
netsci-0.0.4.dist-info/licenses/LICENSE
netsci-0.0.4.dist-info/METADATA
netsci-0.0.4.dist-info/WHEEL
netsci-0.0.4.dist-info/top_level.txt
netsci-0.0.4.dist-info/RECORD
