Metadata-Version: 2.4
Name: netsci
Version: 0.0.4
Summary: Analyzing Complex Networks with Python
Home-page: https://github.com/gialdetti/netsci/
Author: Eyal Gal, Idan Segev, Michael London
Author-email: eyalgl@gmail.com
Classifier: Programming Language :: Python :: 3.10
Classifier: License :: OSI Approved :: GNU General Public License v3 (GPLv3)
License-File: LICENSE
Requires-Dist: numpy>=2.2.6
Requires-Dist: pandas>=2.3.1
Requires-Dist: networkx>=2.2
Requires-Dist: scikit-learn
Requires-Dist: matplotlib
Requires-Dist: seaborn
Provides-Extra: docs
Requires-Dist: black; extra == "docs"
Provides-Extra: test
Requires-Dist: pytest; extra == "test"
Requires-Dist: tox; extra == "test"
Requires-Dist: ipython; extra == "test"
Provides-Extra: dev
Requires-Dist: notebook; extra == "dev"
Requires-Dist: ipywidgets; extra == "dev"
Requires-Dist: altair; extra == "dev"
Requires-Dist: themes; extra == "dev"
Requires-Dist: tqdm; extra == "dev"
Requires-Dist: black; extra == "dev"
Requires-Dist: pytest; extra == "dev"
Requires-Dist: tox; extra == "dev"
Requires-Dist: ipython; extra == "dev"
Dynamic: author
Dynamic: author-email
Dynamic: classifier
Dynamic: description
Dynamic: description-content-type
Dynamic: home-page
Dynamic: license-file
Dynamic: provides-extra
Dynamic: requires-dist
Dynamic: summary
